tapclipy/__init__.py
tapclipy/queries.py
tapclipy/tap_connect.py
tapclipy/textvis.py
tapclipy-0.2.2.dist-info/DESCRIPTION.rst
tapclipy-0.2.2.dist-info/METADATA
tapclipy-0.2.2.dist-info/RECORD
tapclipy-0.2.2.dist-info/WHEEL
tapclipy-0.2.2.dist-info/metadata.json
tapclipy-0.2.2.dist-info/top_level.txt
