Metadata-Version: 2.0
Name: tapclipy
Version: 0.2.2
Summary: Python Client for TAP
Home-page: https://github.com/infosci-qut/tapclipy
Author: andrewresearch
Author-email: UNKNOWN
License: Apache 2.0
Platform: UNKNOWN
